{
  "main": {
    "id": "083c6c6f3db1fe64",
    "type": "split",
    "children": [
      {
        "id": "b46a879b616a8a69",
        "type": "tabs",
        "children": [
          {
            "id": "36f7dee4627b66f5",
            "type": "leaf",
            "state": {
              "type": "markdown",
              "state": {
                "file": "Kubernetes/nigel poulton book/The kubernetes book.md",
                "mode": "source",
                "source": false
              },
              "icon": "lucide-file",
              "title": "The kubernetes book"
            }
          }
        ]
      }
    ],
    "direction": "vertical"
  },
  "left": {
    "id": "7ab7719c3288d843",
    "type": "split",
    "children": [
      {
        "id": "33e1a96c16700712",
        "type": "tabs",
        "children": [
          {
            "id": "1d90df96c6aca71a",
            "type": "leaf",
            "state": {
              "type": "file-explorer",
              "state": {
                "sortOrder": "alphabetical",
                "autoReveal": false
              },
              "icon": "lucide-folder-closed",
              "title": "Files"
            }
          },
          {
            "id": "3e22617f6f6ef775",
            "type": "leaf",
            "state": {
              "type": "search",
              "state": {
                "query": "",
                "matchingCase": false,
                "explainSearch": false,
                "collapseAll": false,
                "extraContext": false,
                "sortOrder": "alphabetical"
              },
              "icon": "lucide-search",
              "title": "Search"
            }
          },
          {
            "id": "479433bf85b5d113",
            "type": "leaf",
            "state": {
              "type": "bookmarks",
              "state": {},
              "icon": "lucide-bookmark",
              "title": "Bookmarks"
            }
          }
        ]
      }
    ],
    "direction": "horizontal",
    "width": 300
  },
  "right": {
    "id": "d0b11bae935bb118",
    "type": "split",
    "children": [
      {
        "id": "4a6182d5583a95de",
        "type": "tabs",
        "children": [
          {
            "id": "8498b5c041ab1488",
            "type": "leaf",
            "state": {
              "type": "backlink",
              "state": {
                "file": "Kubernetes/nigel poulton book/The kubernetes book.md",
                "collapseAll": false,
                "extraContext": false,
                "sortOrder": "alphabetical",
                "showSearch": false,
                "searchQuery": "",
                "backlinkCollapsed": false,
                "unlinkedCollapsed": true
              },
              "icon": "links-coming-in",
              "title": "Backlinks for The kubernetes book"
            }
          },
          {
            "id": "a1fb5876845ac44a",
            "type": "leaf",
            "state": {
              "type": "outgoing-link",
              "state": {
                "file": "Kubernetes/nigel poulton book/The kubernetes book.md",
                "linksCollapsed": false,
                "unlinkedCollapsed": true
              },
              "icon": "links-going-out",
              "title": "Outgoing links from The kubernetes book"
            }
          },
          {
            "id": "7b20724511996070",
            "type": "leaf",
            "state": {
              "type": "tag",
              "state": {
                "sortOrder": "frequency",
                "useHierarchy": true,
                "showSearch": false,
                "searchQuery": ""
              },
              "icon": "lucide-tags",
              "title": "Tags"
            }
          },
          {
            "id": "cc12ea113306cfef",
            "type": "leaf",
            "state": {
              "type": "graph",
              "state": {},
              "icon": "lucide-git-fork",
              "title": "Graph view"
            }
          },
          {
            "id": "1016154841aa8e94",
            "type": "leaf",
            "state": {
              "type": "outline",
              "state": {
                "file": "Kubernetes/nigel poulton book/The kubernetes book.md",
                "followCursor": false,
                "showSearch": false,
                "searchQuery": ""
              },
              "icon": "lucide-list",
              "title": "Outline of The kubernetes book"
            }
          },
          {
            "id": "06fc960ff7a1f831",
            "type": "leaf",
            "state": {
              "type": "calendar",
              "state": {},
              "icon": "calendar-with-checkmark",
              "title": "Calendar"
            }
          },
          {
            "id": "32f16f3be90b8a16",
            "type": "leaf",
            "state": {
              "type": "git-view",
              "state": {},
              "icon": "git-pull-request",
              "title": "Source Control"
            }
          }
        ],
        "currentTab": 6
      }
    ],
    "direction": "horizontal",
    "width": 300
  },
  "left-ribbon": {
    "hiddenItems": {
      "switcher:Open quick switcher": false,
      "graph:Open graph view": false,
      "canvas:Create new canvas": false,
      "daily-notes:Open today's daily note": false,
      "templates:Insert template": false,
      "obsidian-importer:Open Importer": false,
      "command-palette:Open command palette": false,
      "obsidian-git:Open Git source control": false,
      "obsidian-advanced-slides:Show Slide Preview": false
    }
  },
  "active": "36f7dee4627b66f5",
  "lastOpenFiles": [
    "Kubernetes/nigel poulton book/The kubernetes book.md",
    "Kubernetes/nigel poulton book/configmapsk8.png",
    "Work/Angular19.md",
    "Work/Component.md"
  ]
}